CHANGELOG.rst
LICENSE.txt
MANIFEST.in
README.rst
requirements.txt
setup.cfg
setup.py
docs/Makefile
docs/make.bat
docs/source/api.rst
docs/source/changelog.rst
docs/source/conf.py
docs/source/configuration.rst
docs/source/index.rst
docs/source/jobs.rst
docs/source/programs.rst
docs/source/readme.rst
docs/source/utilities.rst
scine_puffin/__init__.py
scine_puffin/__main__.py
scine_puffin/_version.py
scine_puffin/bootstrap.py
scine_puffin/config.py
scine_puffin/daemon.py
scine_puffin/jobloop.py
scine_puffin.egg-info/PKG-INFO
scine_puffin.egg-info/SOURCES.txt
scine_puffin.egg-info/dependency_links.txt
scine_puffin.egg-info/entry_points.txt
scine_puffin.egg-info/not-zip-safe
scine_puffin.egg-info/requires.txt
scine_puffin.egg-info/top_level.txt
scine_puffin/jobs/__init__.py
scine_puffin/jobs/conformers.py
scine_puffin/jobs/dft_embedded_hamiltonian.py
scine_puffin/jobs/gaussian_charge_model_5.py
scine_puffin/jobs/graph.py
scine_puffin/jobs/kinetx_kinetic_modeling.py
scine_puffin/jobs/orca_geometry_optimization.py
scine_puffin/jobs/rms_kinetic_modeling.py
scine_puffin/jobs/scine_afir.py
scine_puffin/jobs/scine_bond_orders.py
scine_puffin/jobs/scine_bspline_optimization.py
scine_puffin/jobs/scine_conceptual_dft.py
scine_puffin/jobs/scine_dissociation_cut.py
scine_puffin/jobs/scine_dissociation_cut_with_optimization.py
scine_puffin/jobs/scine_geometry_optimization.py
scine_puffin/jobs/scine_geometry_validation.py
scine_puffin/jobs/scine_hessian.py
scine_puffin/jobs/scine_irc_scan.py
scine_puffin/jobs/scine_kingfisher.py
scine_puffin/jobs/scine_qm_region_selection.py
scine_puffin/jobs/scine_react_complex_afir.py
scine_puffin/jobs/scine_react_complex_nt.py
scine_puffin/jobs/scine_react_complex_nt2.py
scine_puffin/jobs/scine_react_ts_guess.py
scine_puffin/jobs/scine_single_point.py
scine_puffin/jobs/scine_ts_optimization.py
scine_puffin/jobs/sleep.py
scine_puffin/jobs/swoose_qmmm_forces.py
scine_puffin/jobs/turbomole_bond_orders.py
scine_puffin/jobs/turbomole_geometry_optimization.py
scine_puffin/jobs/turbomole_hessian.py
scine_puffin/jobs/turbomole_single_point.py
scine_puffin/jobs/templates/__init__.py
scine_puffin/jobs/templates/job.py
scine_puffin/jobs/templates/kinetic_modeling_jobs.py
